questradeist/__init__.py
questradeist/account.py
questradeist/auth.py
questradeist/questrade.py
questradeist/symbol.py
questradeist/types.py
questradeist-0.3.4.dist-info/LICENSE
questradeist-0.3.4.dist-info/WHEEL
questradeist-0.3.4.dist-info/METADATA
questradeist-0.3.4.dist-info/RECORD
